Workbook

Sheet Read Me
A1: TrustBank CBS → .NET 10 MVC — Migration Estimate
A4: Prepared from an automated scan of the legacy source on 2026-06-17.
A5: STATUS: Rough Order of Magnitude (ROM), +/-40%. Firm to +/-15% after a 4-6 week discovery (screen-by-screen inventory).
A7: MEASURED SCOPE
A8: - Functional (non-report) screens: 1,059
A9: - Report screens: 399 (+ 892 .rdlc/.rpt report definitions)
A10: - Total .aspx: 1,458 Reusable controls (.ascx): 19 Stored procedures: 5,317
A12: METHOD
A13: - Bottom-up: each functional screen classified Simple/Medium/Complex; reports separate; rate per bucket.
A14: - Plus workstreams: reporting platform, core engine procedures, data migration/parallel-run,
A15: remaining foundation + cross-provider hardening, QA/UAT, security/perf, PM/BA/DevOps/training.
A16: - Calendar = total effort / (team size x productive days per year).
... A33: - Banking correctness/compliance lengthens UAT and may require regulator sign-off.

Sheet Assumptions
A1: TrustBank CBS — Migration Estimate · Assumptions & Rates
A2: All blue cells are editable inputs. Source counts from legacy code scan, 2026-06-17.
A4: Effort rates (person-days per screen)
A5: Simple | B5: 1.5
A6: Medium | B6: 4
A7: Complex | B7: 10
A8: Report | B8: 2
A10: Program parameters
A11: QA + UAT (% of build effort) | B11: 0.3
A12: PM / BA / DevOps / training / docs (% of build) | B12: 0.2
A13: Security review + performance hardening (pd) | B13: 150
A14: Core engine procs to migrate (count) | B14: 40 | C14: interest, balance, day-end, GL posting, clearing
A15: Core engine proc rate (pd each) | B15: 15
A16: Data migration + parallel-run tooling (pd) | B16: 200
A17: Foundation remaining + cross-provider hardening (pd) | B17: 240 | C17: framework is otherwise already built
A18: Reporting platform setup (pd) | B18: 40
A19: Productive days per person-year | B19: 220
A21: Scenario multipliers
A22: Optimistic × | B22: 0.7 | C22: SQL-Server-only, reports rehosted, strong reuse
A23: Likely × | B23: 1
A24: Pessimistic × | B24: 1.4 | C24: multi-DB, full report rebuild, deep parallel-run
A26: Calendar — team sizes (incl. QA/BA/PM)
A27: Team A (people) | B27: 15
A28: Team B (people) | B28: 20
A29: Team C (people) | B29: 25

Sheet Effort Estimate
A1: Migration Effort Estimate
A2: Counts are from the legacy code scan (2026-06-17); rates/parameters live on the Assumptions sheet (editable).
A4: Workstream | B4: Count | C4: Rate (pd) | D4: Effort (pd) | E4: Notes
A5: Simple screens (masters, config, lookups, inquiries) | B5: 121 | C5: =Assumptions!$B$5 | D5: =B5*C5
A6: Medium screens (search/list, multi-tab, dependent pickers) | B6: 751 | C6: =Assumptions!$B$6 | D6: =B6*C6
A7: Complex screens (transactions, maker-checker, calc, batch) | B7: 187 | C7: =Assumptions!$B$7 | D7: =B7*C7
A8: Reports (re-implement) | B8: 399 | C8: =Assumptions!$B$8 | D8: =B8*C8
A9: Reporting platform setup | D9: =Assumptions!$B$18
A10: Core engine procedures | B10: =Assumptions!$B$14 | C10: =Assumptions!$B$15 | D10: =B10*C10
A11: Data migration + parallel-run tooling | D11: =Assumptions!$B$16
A12: Foundation remaining + cross-provider hardening | D12: =Assumptions!$B$17
A13: Build subtotal | D13: =SUM(D5:D12)
A14: QA + UAT | D14: =D13*Assumptions!$B$11
A15: PM / BA / DevOps / training / docs | D15: =D13*Assumptions!$B$12
A16: Security + performance hardening | D16: =Assumptions!$B$13
A17: TOTAL — Likely (pd) | D17: =D13+D14+D15+D16
A19: Scenario | C19: Effort (pd) | D19: Person-years
A20: Optimistic | C20: =$D$17*Assumptions!$B$22 | D20: =C20/Assumptions!$B$19
A21: Likely | C21: =$D$17*Assumptions!$B$23 | D21: =C21/Assumptions!$B$19
A22: Pessimistic | C22: =$D$17*Assumptions!$B$24 | D22: =C22/Assumptions!$B$19
A24: Calendar (Likely) | B24: People | D24: Years
A25: Team A | B25: =Assumptions!$B$27 | D25: =$D$17/(B25*Assumptions!$B$19)
A26: Team B | B26: =Assumptions!$B$28 | D26: =$D$17/(B26*Assumptions!$B$19)
A27: Team C | B27: =Assumptions!$B$29 | D27: =$D$17/(B27*Assumptions!$B$19)

Sheet Module Inventory
A1: Legacy Screens by Module
A2: Auto-classified from the code scan (2026-06-17); complexity is a suggestion to confirm in discovery. Effort uses Assumptions rates.
A4: Module | B4: Simple | C4: Medium | D4: Complex | E4: Report | F4: Total | G4: Est. effort (pd)
A5: RetailBanking | B5: 0 | C5: 535 | D5: 113 | E5: 19 | F5: =SUM(B5:E5) | G5: =B5*Assumptions!$B$5+C5*Assumptions!$B$6+D5*Assumptions!$B$7+E5*Assumptions!$B$8
A6: Reports | B6: 0 | C6: 0 | D6: 0 | E6: 362 | F6: =SUM(B6:E6) | G6: =B6*Assumptions!$B$5+C6*Assumptions!$B$6+D6*Assumptions!$B$7+E6*Assumptions!$B$8
A7: HO | B7: 78 | C7: 120 | D7: 0 | E7: 5 | F7: =SUM(B7:E7) | G7: =B7*Assumptions!$B$5+C7*Assumptions!$B$6+D7*Assumptions!$B$7+E7*Assumptions!$B$8
A8: Reconciliation | B8: 0 | C8: 0 | D8: 74 | E8: 0 | F8: =SUM(B8:E8) | G8: =B8*Assumptions!$B$5+C8*Assumptions!$B$6+D8*Assumptions!$B$7+E8*Assumptions!$B$8
A9: Inventory | B9: 0 | C9: 19 | D9: 0 | E9: 4 | F9: =SUM(B9:E9) | G9: =B9*Assumptions!$B$5+C9*Assumptions!$B$6+D9*Assumptions!$B$7+E9*Assumptions!$B$8
A10: EmployeeDemand | B10: 0 | C10: 21 | D10: 0 | E10: 0 | F10: =SUM(B10:E10) | G10: =B10*Assumptions!$B$5+C10*Assumptions!$B$6+D10*Assumptions!$B$7+E10*Assumptions!$B$8
A11: Helpdesk | B11: 0 | C11: 19 | D11: 0 | E11: 2 | F11: =SUM(B11:E11) | G11: =B11*Assumptions!$B$5+C11*Assumptions!$B$6+D11*Assumptions!$B$7+E11*Assumptions!$B$8
A12: Hr | B12: 2 | C12: 19 | D12: 0 | E12: 0 | F12: =SUM(B12:E12) | G12: =B12*Assumptions!$B$5+C12*Assumptions!$B$6+D12*Assumptions!$B$7+E12*Assumptions!$B$8
A13: Lockers | B13: 15 | C13: 0 | D13: 0 | E13: 0 | F13: =SUM(B13:E13) | G13: =B13*Assumptions!$B$5+C13*Assumptions!$B$6+D13*Assumptions!$B$7+E13*Assumptions!$B$8
A14: (root) | B14: 12 | C14: 0 | D14: 0 | E14: 1 | F14: =SUM(B14:E14) | G14: =B14*Assumptions!$B$5+C14*Assumptions!$B$6+D14*Assumptions!$B$7+E14*Assumptions!$B$8
A15: Config | B15: 6 | C15: 0 | D15: 0 | E15: 2 | F15: =SUM(B15:E15) | G15: =B15*Assumptions!$B$5+C15*Assumptions!$B$6+D15*Assumptions!$B$7+E15*Assumptions!$B$8
A16: Authentication | B16: 7 | C16: 0 | D16: 0 | E16: 0 | F16: =SUM(B16:E16) | G16: =B16*Assumptions!$B$5+C16*Assumptions!$B$6+D16*Assumptions!$B$7+E16*Assumptions!$B$8
... A24: ServiceBranch | B24: 1 | C24: 0 | D24: 0 | E24: 0 | F24: =SUM(B24:E24) | G24: =B24*Assumptions!$B$5+C24*Assumptions!$B$6+D24*Assumptions!$B$7+E24*Assumptions!$B$8
A25: TOTAL | B25: =SUM(B5:B24) | C25: =SUM(C5:C24) | D25: =SUM(D5:D24) | E25: =SUM(E5:E24) | F25: =SUM(F5:F24) | G25: =SUM(G5:G24)

Sheet Screen List
A1: Full Screen Inventory (1 row per .aspx)
A2: Source: legacy Trust.Bank.Publish code scan, 2026-06-17. 'Suggested complexity' is heuristic — confirm in the discovery phase.
A4: Module | B4: Sub-area | C4: Screen | D4: Relative path | E4: Suggested complexity | F4: Est. pd
A5: Authentication | C5: ChooseModule.aspx | D5: Authentication/ChooseModule.aspx | E5: Simple | F5: =VLOOKUP(E5,Assumptions!$A$5:$B$8,2,0)
A6: Authentication | C6: MainMenu.aspx | D6: Authentication/MainMenu.aspx | E6: Simple | F6: =VLOOKUP(E6,Assumptions!$A$5:$B$8,2,0)
A7: Authentication | C7: external_module_handler.aspx | D7: Authentication/external_module_handler.aspx | E7: Simple | F7: =VLOOKUP(E7,Assumptions!$A$5:$B$8,2,0)
A8: Authentication | B8: qrlogin | C8: login_qr_verify.aspx | D8: Authentication/qrlogin/login_qr_verify.aspx | E8: Simple | F8: =VLOOKUP(E8,Assumptions!$A$5:$B$8,2,0)
A9: Authentication | B9: qrlogin | C9: login_qr_verify_handler.aspx | D9: Authentication/qrlogin/login_qr_verify_handler.aspx | E9: Simple | F9: =VLOOKUP(E9,Assumptions!$A$5:$B$8,2,0)
A10: Authentication | B10: qrlogin | C10: qrlogin_register.aspx | D10: Authentication/qrlogin/qrlogin_register.aspx | E10: Simple | F10: =VLOOKUP(E10,Assumptions!$A$5:$B$8,2,0)
A11: Authentication | B11: qrlogin | C11: qrlogin_register_handler.aspx | D11: Authentication/qrlogin/qrlogin_register_handler.aspx | E11: Simple | F11: =VLOOKUP(E11,Assumptions!$A$5:$B$8,2,0)
A12: CcpcClearing | B12: CCPCClearingReports | C12: ReportSettings.aspx | D12: CcpcClearing/CCPCClearingReports/ReportSettings.aspx | E12: Report | F12: =VLOOKUP(E12,Assumptions!$A$5:$B$8,2,0)
A13: Config | C13: AgriReportConfig.aspx | D13: Config/AgriReportConfig.aspx | E13: Report | F13: =VLOOKUP(E13,Assumptions!$A$5:$B$8,2,0)
A14: Config | C14: SGFReportConfig.aspx | D14: Config/SGFReportConfig.aspx | E14: Report | F14: =VLOOKUP(E14,Assumptions!$A$5:$B$8,2,0)
A15: Config | C15: SGFSubMemconnUsers.aspx | D15: Config/SGFSubMemconnUsers.aspx | E15: Simple | F15: =VLOOKUP(E15,Assumptions!$A$5:$B$8,2,0)
A16: Config | C16: UpdateBlockedUser.aspx | D16: Config/UpdateBlockedUser.aspx | E16: Simple | F16: =VLOOKUP(E16,Assumptions!$A$5:$B$8,2,0)
A17: Config | C17: b_MarqueeAlert.aspx | D17: Config/b_MarqueeAlert.aspx | E17: Simple | F17: =VLOOKUP(E17,Assumptions!$A$5:$B$8,2,0)
A18: Config | C18: connectedUsers.aspx | D18: Config/connectedUsers.aspx | E18: Simple | F18: =VLOOKUP(E18,Assumptions!$A$5:$B$8,2,0)
A19: Config | C19: g_CBSShortcutsPopup.aspx | D19: Config/g_CBSShortcutsPopup.aspx | E19: Simple | F19: =VLOOKUP(E19,Assumptions!$A$5:$B$8,2,0)
A20: Config | C20: protectapp.aspx | D20: Config/protectapp.aspx | E20: Simple | F20: =VLOOKUP(E20,Assumptions!$A$5:$B$8,2,0)
A21: Customer360 | C21: Customer360View_v1.aspx | D21: Customer360/Customer360View_v1.aspx | E21: Medium | F21: =VLOOKUP(E21,Assumptions!$A$5:$B$8,2,0)
A22: Customer360 | C22: JointDet360.aspx | D22: Customer360/JointDet360.aspx | E22: Medium | F22: =VLOOKUP(E22,Assumptions!$A$5:$B$8,2,0)
A23: (root) | C23: DashBoard.aspx | D23: DashBoard.aspx | E23: Simple | F23: =VLOOKUP(E23,Assumptions!$A$5:$B$8,2,0)
A24: (root) | C24: EmailCheck.aspx | D24: EmailCheck.aspx | E24: Simple | F24: =VLOOKUP(E24,Assumptions!$A$5:$B$8,2,0)
... A45: EmployeeDemand | C45: UpdateEmployeeDemadAmount.aspx | D45: EmployeeDemand/UpdateEmployeeDemadAmount.aspx | E45: Medium | F45: =VLOOKUP(E45,Assumptions!$A$5:$B$8,2,0)
A46: HO | B46: Admin | C46: A_User.aspx | D46: HO/Admin/A_User.aspx | E46: Medium | F46: =VLOOKUP(E46,Assumptions!$A$5:$B$8,2,0)
A47: HO | B47: Admin | C47: Audit.aspx | D47: HO/Admin/Audit.aspx | E47: Medium | F47: =VLOOKUP(E47,Assumptions!$A$5:$B$8,2,0)
A48: HO | B48: Admin | C48: AuditDetails.aspx | D48: HO/Admin/AuditDetails.aspx | E48: Medium | F48: =VLOOKUP(E48,Assumptions!$A$5:$B$8,2,0)
A49: HO | B49: Admin | C49: AuditView.aspx | D49: HO/Admin/AuditView.aspx | E49: Medium | F49: =VLOOKUP(E49,Assumptions!$A$5:$B$8,2,0)
A50: HO | B50: Admin | C50: ChangePassword.aspx | D50: HO/Admin/ChangePassword.aspx | E50: Medium | F50: =VLOOKUP(E50,Assumptions!$A$5:$B$8,2,0)
A51: HO | B51: Admin | C51: ForgotPassword.aspx | D51: HO/Admin/ForgotPassword.aspx | E51: Medium | F51: =VLOOKUP(E51,Assumptions!$A$5:$B$8,2,0)
A52: HO | B52: Admin | C52: PasswordPolicyConfig.aspx | D52: HO/Admin/PasswordPolicyConfig.aspx | E52: Medium | F52: =VLOOKUP(E52,Assumptions!$A$5:$B$8,2,0)
A53: HO | B53: Admin | C53: Pop-up.aspx | D53: HO/Admin/Pop-up.aspx | E53: Medium | F53: =VLOOKUP(E53,Assumptions!$A$5:$B$8,2,0)
A54: HO | B54: Admin | C54: a_AutoGenerateUser.aspx | D54: HO/Admin/a_AutoGenerateUser.aspx | E54: Medium | F54: =VLOOKUP(E54,Assumptions!$A$5:$B$8,2,0)
A55: HO | B55: Admin | C55: a_BrLoginAccessTime.aspx | D55: HO/Admin/a_BrLoginAccessTime.aspx | E55: Medium | F55: =VLOOKUP(E55,Assumptions!$A$5:$B$8,2,0)
A56: HO | B56: Admin | C56: a_CashierLimit.aspx | D56: HO/Admin/a_CashierLimit.aspx | E56: Medium | F56: =VLOOKUP(E56,Assumptions!$A$5:$B$8,2,0)
A57: HO | B57: Admin | C57: a_ChangePassword.aspx | D57: HO/Admin/a_ChangePassword.aspx | E57: Medium | F57: =VLOOKUP(E57,Assumptions!$A$5:$B$8,2,0)
... A104: HO | B104: Bank | C104: g_Title.aspx | D104: HO/Bank/g_Title.aspx | E104: Simple | F104: =VLOOKUP(E104,Assumptions!$A$5:$B$8,2,0)
A105: HO | C105: BankVariableConfig.aspx | D105: HO/BankVariableConfig.aspx | E105: Medium | F105: =VLOOKUP(E105,Assumptions!$A$5:$B$8,2,0)
A106: HO | C106: BranchVariableConfig.aspx | D106: HO/BranchVariableConfig.aspx | E106: Medium | F106: =VLOOKUP(E106,Assumptions!$A$5:$B$8,2,0)
A107: HO | C107: DeductMinBalHeadMap.aspx | D107: HO/DeductMinBalHeadMap.aspx | E107: Medium | F107: =VLOOKUP(E107,Assumptions!$A$5:$B$8,2,0)
A108: HO | B108: ECS | C108: EcsMandateCancelPopup.aspx | D108: HO/ECS/EcsMandateCancelPopup.aspx | E108: Medium | F108: =VLOOKUP(E108,Assumptions!$A$5:$B$8,2,0)
A109: HO | B109: ECS | C109: x_EcsMandateNew.aspx | D109: HO/ECS/x_EcsMandateNew.aspx | E109: Medium | F109: =VLOOKUP(E109,Assumptions!$A$5:$B$8,2,0)
A110: HO | C110: GSTTransactionDetail.aspx | D110: HO/GSTTransactionDetail.aspx | E110: Medium | F110: =VLOOKUP(E110,Assumptions!$A$5:$B$8,2,0)
A111: HO | C111: GlobalClientDocAttach.aspx | D111: HO/GlobalClientDocAttach.aspx | E111: Medium | F111: =VLOOKUP(E111,Assumptions!$A$5:$B$8,2,0)
A112: HO | C112: GlobalClientDocAttachPopup.aspx | D112: HO/GlobalClientDocAttachPopup.aspx | E112: Medium | F112: =VLOOKUP(E112,Assumptions!$A$5:$B$8,2,0)
A113: HO | B113: Hr | C113: g_BankDirRelative.aspx | D113: HO/Hr/g_BankDirRelative.aspx | E113: Simple | F113: =VLOOKUP(E113,Assumptions!$A$5:$B$8,2,0)
A114: HO | B114: Hr | C114: g_BankDirectors.aspx | D114: HO/Hr/g_BankDirectors.aspx | E114: Simple | F114: =VLOOKUP(E114,Assumptions!$A$5:$B$8,2,0)
A115: HO | B115: Hr | C115: h_EmpDeputationExt.aspx | D115: HO/Hr/h_EmpDeputationExt.aspx | E115: Medium | F115: =VLOOKUP(E115,Assumptions!$A$5:$B$8,2,0)
A116: HO | B116: Hr | C116: h_Employee.aspx | D116: HO/Hr/h_Employee.aspx | E116: Medium | F116: =VLOOKUP(E116,Assumptions!$A$5:$B$8,2,0)
A117: HO | B117: Hr | C117: h_EmployeeDeputation.aspx | D117: HO/Hr/h_EmployeeDeputation.aspx | E117: Medium | F117: =VLOOKUP(E117,Assumptions!$A$5:$B$8,2,0)
A118: HO | B118: Hr | C118: h_EmployeeRelease.aspx | D118: HO/Hr/h_EmployeeRelease.aspx | E118: Medium | F118: =VLOOKUP(E118,Assumptions!$A$5:$B$8,2,0)
A119: HO | C119: KYCClientPopup.aspx | D119: HO/KYCClientPopup.aspx | E119: Medium | F119: =VLOOKUP(E119,Assumptions!$A$5:$B$8,2,0)
A120: HO | C120: KYCClientPopup_V1.aspx | D120: HO/KYCClientPopup_V1.aspx | E120: Medium | F120: =VLOOKUP(E120,Assumptions!$A$5:$B$8,2,0)
A121: HO | C121: KYCUpdateInfo.aspx | D121: HO/KYCUpdateInfo.aspx | E121: Medium | F121: =VLOOKUP(E121,Assumptions!$A$5:$B$8,2,0)
A122: HO | C122: MbankGlobalAccLimit.aspx | D122: HO/MbankGlobalAccLimit.aspx | E122: Medium | F122: =VLOOKUP(E122,Assumptions!$A$5:$B$8,2,0)
A123: HO | C123: PigmyContraMaping.aspx | D123: HO/PigmyContraMaping.aspx | E123: Medium | F123: =VLOOKUP(E123,Assumptions!$A$5:$B$8,2,0)
A124: HO | B124: ProjectFormulation | C124: C_LoanDocCollection.aspx | D124: HO/ProjectFormulation/C_LoanDocCollection.aspx | E124: Medium | F124: =VLOOKUP(E124,Assumptions!$A$5:$B$8,2,0)
A125: HO | B125: ProjectFormulation | C125: P_CreditOfficer.aspx | D125: HO/ProjectFormulation/P_CreditOfficer.aspx | E125: Medium | F125: =VLOOKUP(E125,Assumptions!$A$5:$B$8,2,0)
A126: HO | B126: ProjectFormulation | C126: c_LoanDocRelease.aspx | D126: HO/ProjectFormulation/c_LoanDocRelease.aspx | E126: Medium | F126: =VLOOKUP(E126,Assumptions!$A$5:$B$8,2,0)
A127: HO | B127: ProjectFormulation | C127: p_AnnexPre.aspx | D127: HO/ProjectFormulation/p_AnnexPre.aspx | E127: Medium | F127: =VLOOKUP(E127,Assumptions!$A$5:$B$8,2,0)
A128: HO | B128: ProjectFormulation | C128: p_Applicant.aspx | D128: HO/ProjectFormulation/p_Applicant.aspx | E128: Medium | F128: =VLOOKUP(E128,Assumptions!$A$5:$B$8,2,0)
A129: HO | B129: ProjectFormulation | C129: p_CommitteeDirectors.aspx | D129: HO/ProjectFormulation/p_CommitteeDirectors.aspx | E129: Medium | F129: =VLOOKUP(E129,Assumptions!$A$5:$B$8,2,0)
A130: HO | B130: ProjectFormulation | C130: p_CommitteeMaster.aspx | D130: HO/ProjectFormulation/p_CommitteeMaster.aspx | E130: Medium | F130: =VLOOKUP(E130,Assumptions!$A$5:$B$8,2,0)
A131: HO | B131: ProjectFormulation | C131: p_CommitteeMasterMemberAP.aspx | D131: HO/ProjectFormulation/p_CommitteeMasterMemberAP.aspx | E131: Medium | F131: =VLOOKUP(E131,Assumptions!$A$5:$B$8,2,0)
A132: HO | B132: ProjectFormulation | C132: p_CommitteeMasterMemberAR.aspx | D132: HO/ProjectFormulation/p_CommitteeMasterMemberAR.aspx | E132: Medium | F132: =VLOOKUP(E132,Assumptions!$A$5:$B$8,2,0)
A133: HO | B133: ProjectFormulation | C133: p_Document.aspx | D133: HO/ProjectFormulation/p_Document.aspx | E133: Medium | F133: =VLOOKUP(E133,Assumptions!$A$5:$B$8,2,0)
A134: HO | B134: ProjectFormulation | C134: p_LoanCaseCommitteeRemarks.aspx | D134: HO/ProjectFormulation/p_LoanCaseCommitteeRemarks.aspx | E134: Medium | F134: =VLOOKUP(E134,Assumptions!$A$5:$B$8,2,0)
A135: HO | B135: ProjectFormulation | C135: p_LoanCase_v1.aspx | D135: HO/ProjectFormulation/p_LoanCase_v1.aspx | E135: Medium | F135: =VLOOKUP(E135,Assumptions!$A$5:$B$8,2,0)
... A207: HO | B207: Retailbanking | C207: x_TdsReversal.aspx | D207: HO/Retailbanking/x_TdsReversal.aspx | E207: Medium | F207: =VLOOKUP(E207,Assumptions!$A$5:$B$8,2,0)
A208: HO | C208: SMSAutoConfig.aspx | D208: HO/SMSAutoConfig.aspx | E208: Medium | F208: =VLOOKUP(E208,Assumptions!$A$5:$B$8,2,0)
A209: HO | C209: SignaturePreview.aspx | D209: HO/SignaturePreview.aspx | E209: Medium | F209: =VLOOKUP(E209,Assumptions!$A$5:$B$8,2,0)
A210: HO | C210: SmsConfig.aspx | D210: HO/SmsConfig.aspx | E210: Medium | F210: =VLOOKUP(E210,Assumptions!$A$5:$B$8,2,0)
A211: HO | C211: SubMemSubStatus.aspx | D211: HO/SubMemSubStatus.aspx | E211: Medium | F211: =VLOOKUP(E211,Assumptions!$A$5:$B$8,2,0)
A212: HO | C212: Sys_AccessControl.aspx | D212: HO/Sys_AccessControl.aspx | E212: Medium | F212: =VLOOKUP(E212,Assumptions!$A$5:$B$8,2,0)
A213: HO | C213: Sys_MetaData.aspx | D213: HO/Sys_MetaData.aspx | E213: Medium | F213: =VLOOKUP(E213,Assumptions!$A$5:$B$8,2,0)
A214: HO | C214: TerroristGroupdetails.aspx | D214: HO/TerroristGroupdetails.aspx | E214: Medium | F214: =VLOOKUP(E214,Assumptions!$A$5:$B$8,2,0)
A215: HO | C215: TerroristGroupdetails_V1.aspx | D215: HO/TerroristGroupdetails_V1.aspx | E215: Medium | F215: =VLOOKUP(E215,Assumptions!$A$5:$B$8,2,0)
A216: HO | C216: VerifyAadhar.aspx | D216: HO/VerifyAadhar.aspx | E216: Medium | F216: =VLOOKUP(E216,Assumptions!$A$5:$B$8,2,0)
A217: HO | C217: VerifyDocuments.aspx | D217: HO/VerifyDocuments.aspx | E217: Medium | F217: =VLOOKUP(E217,Assumptions!$A$5:$B$8,2,0)
A218: HO | C218: VerifyPancard.aspx | D218: HO/VerifyPancard.aspx | E218: Medium | F218: =VLOOKUP(E218,Assumptions!$A$5:$B$8,2,0)
A219: HO | C219: a_UserOtherBranchLogin.aspx | D219: HO/a_UserOtherBranchLogin.aspx | E219: Medium | F219: =VLOOKUP(E219,Assumptions!$A$5:$B$8,2,0)
... A236: HO | C236: b_clientv2.aspx | D236: HO/b_clientv2.aspx | E236: Simple | F236: =VLOOKUP(E236,Assumptions!$A$5:$B$8,2,0)
A237: HO | B237: client_image_verify | C237: client_doc_verify.aspx | D237: HO/client_image_verify/client_doc_verify.aspx | E237: Medium | F237: =VLOOKUP(E237,Assumptions!$A$5:$B$8,2,0)
A238: HO | B238: client_image_verify | C238: client_doc_verify_handler.aspx | D238: HO/client_image_verify/client_doc_verify_handler.aspx | E238: Medium | F238: =VLOOKUP(E238,Assumptions!$A$5:$B$8,2,0)
A239: HO | C239: g_BlackListedDomain.aspx | D239: HO/g_BlackListedDomain.aspx | E239: Simple | F239: =VLOOKUP(E239,Assumptions!$A$5:$B$8,2,0)
A240: HO | C240: g_ClientGroup.aspx | D240: HO/g_ClientGroup.aspx | E240: Simple | F240: =VLOOKUP(E240,Assumptions!$A$5:$B$8,2,0)
A241: HO | C241: g_ClientIncomeDet.aspx | D241: HO/g_ClientIncomeDet.aspx | E241: Simple | F241: =VLOOKUP(E241,Assumptions!$A$5:$B$8,2,0)
A242: HO | C242: g_CustomerOnBoarding.aspx | D242: HO/g_CustomerOnBoarding.aspx | E242: Simple | F242: =VLOOKUP(E242,Assumptions!$A$5:$B$8,2,0)
A243: HO | C243: g_PigmyCommisionMapping.aspx | D243: HO/g_PigmyCommisionMapping.aspx | E243: Simple | F243: =VLOOKUP(E243,Assumptions!$A$5:$B$8,2,0)
A244: HO | C244: sys_AutoProcessConfig.aspx | D244: HO/sys_AutoProcessConfig.aspx | E244: Medium | F244: =VLOOKUP(E244,Assumptions!$A$5:$B$8,2,0)
A245: HO | C245: x_GetGstData.aspx | D245: HO/x_GetGstData.aspx | E245: Medium | F245: =VLOOKUP(E245,Assumptions!$A$5:$B$8,2,0)
A246: HO | C246: x_GstGLBalanceReport.aspx | D246: HO/x_GstGLBalanceReport.aspx | E246: Report | F246: =VLOOKUP(E246,Assumptions!$A$5:$B$8,2,0)
A247: HO | C247: x_IncomeGSTTrans.aspx | D247: HO/x_IncomeGSTTrans.aspx | E247: Medium | F247: =VLOOKUP(E247,Assumptions!$A$5:$B$8,2,0)
A248: HO | C248: x_IncomeGSTTransV1.aspx | D248: HO/x_IncomeGSTTransV1.aspx | E248: Medium | F248: =VLOOKUP(E248,Assumptions!$A$5:$B$8,2,0)
A249: Helpdesk | C249: HD_TranLimitslab.aspx | D249: Helpdesk/HD_TranLimitslab.aspx | E249: Medium | F249: =VLOOKUP(E249,Assumptions!$A$5:$B$8,2,0)
A250: Helpdesk | C250: HelpDeskPasswordPolicyConfig.aspx | D250: Helpdesk/HelpDeskPasswordPolicyConfig.aspx | E250: Medium | F250: =VLOOKUP(E250,Assumptions!$A$5:$B$8,2,0)
... A405: Reconciliation | C405: re_TheirLedgerExcelDataTransfer.aspx | D405: Reconciliation/re_TheirLedgerExcelDataTransfer.aspx | E405: Complex | F405: =VLOOKUP(E405,Assumptions!$A$5:$B$8,2,0)
A406: Reports | B406: Admin | C406: AdminDatalogreport.aspx | D406: Reports/Admin/AdminDatalogreport.aspx | E406: Report | F406: =VLOOKUP(E406,Assumptions!$A$5:$B$8,2,0)
A407: Reports | B407: Admin | C407: AdminReport.aspx | D407: Reports/Admin/AdminReport.aspx | E407: Report | F407: =VLOOKUP(E407,Assumptions!$A$5:$B$8,2,0)
A408: Reports | B408: Admin | C408: BankBranchLogReport.aspx | D408: Reports/Admin/BankBranchLogReport.aspx | E408: Report | F408: =VLOOKUP(E408,Assumptions!$A$5:$B$8,2,0)
...
